<?xml version="1.0" encoding="UTF-8"?>
<objects serializationModel="Studio.02.02.00">
	<object class="AudioFile" id="{6ce59d45-5715-4d0b-8ff0-24edcdb30551}">
		<property name="assetPath">
			<value>Player/Rotate (2).wav</value>
		</property>
		<property name="frequencyInKHz">
			<value>11.0249996</value>
		</property>
		<property name="channelCount">
			<value>1</value>
		</property>
		<property name="length">
			<value>0.47455782312925171</value>
		</property>
		<relationship name="masterAssetFolder">
			<destination>{049e32d2-ea6e-4dd0-9e34-6933250b68c3}</destination>
		</relationship>
	</object>
</objects>
